textkernel/_DATA_GRAMMAR.py
textkernel/_NAME_GRAMMAR.py
textkernel/_PREDEFINED_BODY_INFO.py
textkernel/_PREDEFINED_FRAME_INFO.py
textkernel/__init__.py
textkernel/_version.py
textkernel/SPICE_N0067/zzfdat.f
textkernel/SPICE_N0067/zzidmap.f
rms_textkernel-1.0.5.dist-info/LICENSE
rms_textkernel-1.0.5.dist-info/METADATA
rms_textkernel-1.0.5.dist-info/WHEEL
rms_textkernel-1.0.5.dist-info/top_level.txt
rms_textkernel-1.0.5.dist-info/RECORD
